{
  "asof": "2026-05-18T04:00:00Z",
  "windows": {
    "yesterday": {
      "summary": {
        "picks": 14,
        "wins": 6,
        "losses": 8,
        "pushes": 0,
        "voids": 0,
        "units": -3.1822,
        "totalStake": 14.0,
        "winRate": 0.4286,
        "roi": -0.2273
      },
      "byMarket": {
        "Total": {
          "picks": 2,
          "wins": 2,
          "losses": 0,
          "pushes": 0,
          "voids": 0,
          "units": 1.8182,
          "totalStake": 2.0,
          "winRate": 1.0,
          "roi": 0.9091
        },
        "K": {
          "picks": 2,
          "wins": 0,
          "losses": 2,
          "pushes": 0,
          "voids": 0,
          "units": -2.0,
          "totalStake": 2.0,
          "winRate": 0.0,
          "roi": -1.0
        },
        "ML": {
          "picks": 10,
          "wins": 4,
          "losses": 6,
          "pushes": 0,
          "voids": 0,
          "units": -3.0004,
          "totalStake": 10.0,
          "winRate": 0.4,
          "roi": -0.3
        }
      },
      "byTier": {
        "b": {
          "picks": 6,
          "wins": 4,
          "losses": 2,
          "pushes": 0,
          "voids": 0,
          "units": 1.1023,
          "totalStake": 6.0,
          "winRate": 0.6667,
          "roi": 0.1837
        },
        "c": {
          "picks": 8,
          "wins": 2,
          "losses": 6,
          "pushes": 0,
          "voids": 0,
          "units": -4.2845,
          "totalStake": 8.0,
          "winRate": 0.25,
          "roi": -0.5356
        }
      }
    },
    "recent7": {
      "summary": {
        "picks": 243,
        "wins": 113,
        "losses": 94,
        "pushes": 10,
        "voids": 26,
        "units": -5.4064,
        "totalStake": 217.0,
        "winRate": 0.5459,
        "roi": -0.0249
      },
      "byMarket": {
        "F5_ML": {
          "picks": 46,
          "wins": 26,
          "losses": 12,
          "pushes": 8,
          "voids": 0,
          "units": 8.8848,
          "totalStake": 46.0,
          "winRate": 0.6842,
          "roi": 0.1931
        },
        "Hits": {
          "picks": 71,
          "wins": 23,
          "losses": 23,
          "pushes": 0,
          "voids": 25,
          "units": -9.7274,
          "totalStake": 46.0,
          "winRate": 0.5,
          "roi": -0.2115
        },
        "ML": {
          "picks": 59,
          "wins": 30,
          "losses": 29,
          "pushes": 0,
          "voids": 0,
          "units": -6.4846,
          "totalStake": 59.0,
          "winRate": 0.5085,
          "roi": -0.1099
        },
        "TotalBases": {
          "picks": 4,
          "wins": 2,
          "losses": 1,
          "pushes": 0,
          "voids": 1,
          "units": 1.9,
          "totalStake": 3.0,
          "winRate": 0.6667,
          "roi": 0.6333
        },
        "Total": {
          "picks": 42,
          "wins": 21,
          "losses": 19,
          "pushes": 2,
          "voids": 0,
          "units": 0.0965,
          "totalStake": 42.0,
          "winRate": 0.525,
          "roi": 0.0023
        },
        "K": {
          "picks": 19,
          "wins": 10,
          "losses": 9,
          "pushes": 0,
          "voids": 0,
          "units": -0.2757,
          "totalStake": 19.0,
          "winRate": 0.5263,
          "roi": -0.0145
        },
        "RL": {
          "picks": 2,
          "wins": 1,
          "losses": 1,
          "pushes": 0,
          "voids": 0,
          "units": 0.2,
          "totalStake": 2.0,
          "winRate": 0.5,
          "roi": 0.1
        }
      },
      "byTier": {
        "watch": {
          "picks": 131,
          "wins": 57,
          "losses": 47,
          "pushes": 8,
          "voids": 19,
          "units": -0.4943,
          "totalStake": 112.0,
          "winRate": 0.5481,
          "roi": -0.0044
        },
        "B": {
          "picks": 69,
          "wins": 34,
          "losses": 30,
          "pushes": 1,
          "voids": 4,
          "units": -4.0977,
          "totalStake": 65.0,
          "winRate": 0.5312,
          "roi": -0.063
        },
        "C": {
          "picks": 23,
          "wins": 12,
          "losses": 9,
          "pushes": 0,
          "voids": 2,
          "units": -0.6918,
          "totalStake": 21.0,
          "winRate": 0.5714,
          "roi": -0.0329
        },
        "A": {
          "picks": 6,
          "wins": 4,
          "losses": 0,
          "pushes": 1,
          "voids": 1,
          "units": 3.0596,
          "totalStake": 5.0,
          "winRate": 1.0,
          "roi": 0.6119
        },
        "b": {
          "picks": 6,
          "wins": 4,
          "losses": 2,
          "pushes": 0,
          "voids": 0,
          "units": 1.1023,
          "totalStake": 6.0,
          "winRate": 0.6667,
          "roi": 0.1837
        },
        "c": {
          "picks": 8,
          "wins": 2,
          "losses": 6,
          "pushes": 0,
          "voids": 0,
          "units": -4.2845,
          "totalStake": 8.0,
          "winRate": 0.25,
          "roi": -0.5356
        }
      }
    },
    "recent14": {
      "summary": {
        "picks": 676,
        "wins": 336,
        "losses": 266,
        "pushes": 22,
        "voids": 52,
        "units": 29.6785,
        "totalStake": 624.0,
        "winRate": 0.5581,
        "roi": 0.0476
      },
      "byMarket": {
        "F5_ML": {
          "picks": 139,
          "wins": 67,
          "losses": 52,
          "pushes": 18,
          "voids": 2,
          "units": 9.1983,
          "totalStake": 137.0,
          "winRate": 0.563,
          "roi": 0.0671
        },
        "Hits": {
          "picks": 166,
          "wins": 73,
          "losses": 52,
          "pushes": 0,
          "voids": 41,
          "units": 5.5529,
          "totalStake": 125.0,
          "winRate": 0.584,
          "roi": 0.0444
        },
        "K": {
          "picks": 36,
          "wins": 17,
          "losses": 17,
          "pushes": 0,
          "voids": 2,
          "units": -2.1789,
          "totalStake": 34.0,
          "winRate": 0.5,
          "roi": -0.0641
        },
        "ML": {
          "picks": 174,
          "wins": 85,
          "losses": 86,
          "pushes": 0,
          "voids": 3,
          "units": -11.3574,
          "totalStake": 171.0,
          "winRate": 0.4971,
          "roi": -0.0664
        },
        "Total": {
          "picks": 142,
          "wins": 86,
          "losses": 51,
          "pushes": 3,
          "voids": 2,
          "units": 27.3698,
          "totalStake": 140.0,
          "winRate": 0.6277,
          "roi": 0.1955
        },
        "RL": {
          "picks": 7,
          "wins": 5,
          "losses": 2,
          "pushes": 0,
          "voids": 0,
          "units": 3.2847,
          "totalStake": 7.0,
          "winRate": 0.7143,
          "roi": 0.4692
        },
        "F5_Total": {
          "picks": 4,
          "wins": 0,
          "losses": 3,
          "pushes": 1,
          "voids": 0,
          "units": -3.0,
          "totalStake": 4.0,
          "winRate": 0.0,
          "roi": -0.75
        },
        "NRFI": {
          "picks": 1,
          "wins": 0,
          "losses": 1,
          "pushes": 0,
          "voids": 0,
          "units": -1.0,
          "totalStake": 1.0,
          "winRate": 0.0,
          "roi": -1.0
        },
        "TotalBases": {
          "picks": 7,
          "wins": 3,
          "losses": 2,
          "pushes": 0,
          "voids": 2,
          "units": 1.8091,
          "totalStake": 5.0,
          "winRate": 0.6,
          "roi": 0.3618
        }
      },
      "byTier": {
        "watch": {
          "picks": 452,
          "wins": 219,
          "losses": 174,
          "pushes": 17,
          "voids": 42,
          "units": 23.8171,
          "totalStake": 410.0,
          "winRate": 0.5573,
          "roi": 0.0581
        },
        "B": {
          "picks": 158,
          "wins": 85,
          "losses": 63,
          "pushes": 4,
          "voids": 6,
          "units": 9.1562,
          "totalStake": 152.0,
          "winRate": 0.5743,
          "roi": 0.0602
        },
        "C": {
          "picks": 43,
          "wins": 20,
          "losses": 20,
          "pushes": 0,
          "voids": 3,
          "units": -3.9904,
          "totalStake": 40.0,
          "winRate": 0.5,
          "roi": -0.0998
        },
        "A": {
          "picks": 9,
          "wins": 6,
          "losses": 1,
          "pushes": 1,
          "voids": 1,
          "units": 3.8778,
          "totalStake": 8.0,
          "winRate": 0.8571,
          "roi": 0.4847
        },
        "b": {
          "picks": 6,
          "wins": 4,
          "losses": 2,
          "pushes": 0,
          "voids": 0,
          "units": 1.1023,
          "totalStake": 6.0,
          "winRate": 0.6667,
          "roi": 0.1837
        },
        "c": {
          "picks": 8,
          "wins": 2,
          "losses": 6,
          "pushes": 0,
          "voids": 0,
          "units": -4.2845,
          "totalStake": 8.0,
          "winRate": 0.25,
          "roi": -0.5356
        }
      }
    },
    "recent30": {
      "summary": {
        "picks": 676,
        "wins": 336,
        "losses": 266,
        "pushes": 22,
        "voids": 52,
        "units": 29.6785,
        "totalStake": 624.0,
        "winRate": 0.5581,
        "roi": 0.0476
      },
      "byMarket": {
        "F5_ML": {
          "picks": 139,
          "wins": 67,
          "losses": 52,
          "pushes": 18,
          "voids": 2,
          "units": 9.1983,
          "totalStake": 137.0,
          "winRate": 0.563,
          "roi": 0.0671
        },
        "Hits": {
          "picks": 166,
          "wins": 73,
          "losses": 52,
          "pushes": 0,
          "voids": 41,
          "units": 5.5529,
          "totalStake": 125.0,
          "winRate": 0.584,
          "roi": 0.0444
        },
        "K": {
          "picks": 36,
          "wins": 17,
          "losses": 17,
          "pushes": 0,
          "voids": 2,
          "units": -2.1789,
          "totalStake": 34.0,
          "winRate": 0.5,
          "roi": -0.0641
        },
        "ML": {
          "picks": 174,
          "wins": 85,
          "losses": 86,
          "pushes": 0,
          "voids": 3,
          "units": -11.3574,
          "totalStake": 171.0,
          "winRate": 0.4971,
          "roi": -0.0664
        },
        "Total": {
          "picks": 142,
          "wins": 86,
          "losses": 51,
          "pushes": 3,
          "voids": 2,
          "units": 27.3698,
          "totalStake": 140.0,
          "winRate": 0.6277,
          "roi": 0.1955
        },
        "RL": {
          "picks": 7,
          "wins": 5,
          "losses": 2,
          "pushes": 0,
          "voids": 0,
          "units": 3.2847,
          "totalStake": 7.0,
          "winRate": 0.7143,
          "roi": 0.4692
        },
        "F5_Total": {
          "picks": 4,
          "wins": 0,
          "losses": 3,
          "pushes": 1,
          "voids": 0,
          "units": -3.0,
          "totalStake": 4.0,
          "winRate": 0.0,
          "roi": -0.75
        },
        "NRFI": {
          "picks": 1,
          "wins": 0,
          "losses": 1,
          "pushes": 0,
          "voids": 0,
          "units": -1.0,
          "totalStake": 1.0,
          "winRate": 0.0,
          "roi": -1.0
        },
        "TotalBases": {
          "picks": 7,
          "wins": 3,
          "losses": 2,
          "pushes": 0,
          "voids": 2,
          "units": 1.8091,
          "totalStake": 5.0,
          "winRate": 0.6,
          "roi": 0.3618
        }
      },
      "byTier": {
        "watch": {
          "picks": 452,
          "wins": 219,
          "losses": 174,
          "pushes": 17,
          "voids": 42,
          "units": 23.8171,
          "totalStake": 410.0,
          "winRate": 0.5573,
          "roi": 0.0581
        },
        "B": {
          "picks": 158,
          "wins": 85,
          "losses": 63,
          "pushes": 4,
          "voids": 6,
          "units": 9.1562,
          "totalStake": 152.0,
          "winRate": 0.5743,
          "roi": 0.0602
        },
        "C": {
          "picks": 43,
          "wins": 20,
          "losses": 20,
          "pushes": 0,
          "voids": 3,
          "units": -3.9904,
          "totalStake": 40.0,
          "winRate": 0.5,
          "roi": -0.0998
        },
        "A": {
          "picks": 9,
          "wins": 6,
          "losses": 1,
          "pushes": 1,
          "voids": 1,
          "units": 3.8778,
          "totalStake": 8.0,
          "winRate": 0.8571,
          "roi": 0.4847
        },
        "b": {
          "picks": 6,
          "wins": 4,
          "losses": 2,
          "pushes": 0,
          "voids": 0,
          "units": 1.1023,
          "totalStake": 6.0,
          "winRate": 0.6667,
          "roi": 0.1837
        },
        "c": {
          "picks": 8,
          "wins": 2,
          "losses": 6,
          "pushes": 0,
          "voids": 0,
          "units": -4.2845,
          "totalStake": 8.0,
          "winRate": 0.25,
          "roi": -0.5356
        }
      }
    },
    "lifetime": {
      "summary": {
        "picks": 676,
        "wins": 336,
        "losses": 266,
        "pushes": 22,
        "voids": 52,
        "units": 29.6785,
        "totalStake": 624.0,
        "winRate": 0.5581,
        "roi": 0.0476
      },
      "byMarket": {
        "F5_ML": {
          "picks": 139,
          "wins": 67,
          "losses": 52,
          "pushes": 18,
          "voids": 2,
          "units": 9.1983,
          "totalStake": 137.0,
          "winRate": 0.563,
          "roi": 0.0671
        },
        "Hits": {
          "picks": 166,
          "wins": 73,
          "losses": 52,
          "pushes": 0,
          "voids": 41,
          "units": 5.5529,
          "totalStake": 125.0,
          "winRate": 0.584,
          "roi": 0.0444
        },
        "K": {
          "picks": 36,
          "wins": 17,
          "losses": 17,
          "pushes": 0,
          "voids": 2,
          "units": -2.1789,
          "totalStake": 34.0,
          "winRate": 0.5,
          "roi": -0.0641
        },
        "ML": {
          "picks": 174,
          "wins": 85,
          "losses": 86,
          "pushes": 0,
          "voids": 3,
          "units": -11.3574,
          "totalStake": 171.0,
          "winRate": 0.4971,
          "roi": -0.0664
        },
        "Total": {
          "picks": 142,
          "wins": 86,
          "losses": 51,
          "pushes": 3,
          "voids": 2,
          "units": 27.3698,
          "totalStake": 140.0,
          "winRate": 0.6277,
          "roi": 0.1955
        },
        "RL": {
          "picks": 7,
          "wins": 5,
          "losses": 2,
          "pushes": 0,
          "voids": 0,
          "units": 3.2847,
          "totalStake": 7.0,
          "winRate": 0.7143,
          "roi": 0.4692
        },
        "F5_Total": {
          "picks": 4,
          "wins": 0,
          "losses": 3,
          "pushes": 1,
          "voids": 0,
          "units": -3.0,
          "totalStake": 4.0,
          "winRate": 0.0,
          "roi": -0.75
        },
        "NRFI": {
          "picks": 1,
          "wins": 0,
          "losses": 1,
          "pushes": 0,
          "voids": 0,
          "units": -1.0,
          "totalStake": 1.0,
          "winRate": 0.0,
          "roi": -1.0
        },
        "TotalBases": {
          "picks": 7,
          "wins": 3,
          "losses": 2,
          "pushes": 0,
          "voids": 2,
          "units": 1.8091,
          "totalStake": 5.0,
          "winRate": 0.6,
          "roi": 0.3618
        }
      },
      "byTier": {
        "watch": {
          "picks": 452,
          "wins": 219,
          "losses": 174,
          "pushes": 17,
          "voids": 42,
          "units": 23.8171,
          "totalStake": 410.0,
          "winRate": 0.5573,
          "roi": 0.0581
        },
        "B": {
          "picks": 158,
          "wins": 85,
          "losses": 63,
          "pushes": 4,
          "voids": 6,
          "units": 9.1562,
          "totalStake": 152.0,
          "winRate": 0.5743,
          "roi": 0.0602
        },
        "C": {
          "picks": 43,
          "wins": 20,
          "losses": 20,
          "pushes": 0,
          "voids": 3,
          "units": -3.9904,
          "totalStake": 40.0,
          "winRate": 0.5,
          "roi": -0.0998
        },
        "A": {
          "picks": 9,
          "wins": 6,
          "losses": 1,
          "pushes": 1,
          "voids": 1,
          "units": 3.8778,
          "totalStake": 8.0,
          "winRate": 0.8571,
          "roi": 0.4847
        },
        "b": {
          "picks": 6,
          "wins": 4,
          "losses": 2,
          "pushes": 0,
          "voids": 0,
          "units": 1.1023,
          "totalStake": 6.0,
          "winRate": 0.6667,
          "roi": 0.1837
        },
        "c": {
          "picks": 8,
          "wins": 2,
          "losses": 6,
          "pushes": 0,
          "voids": 0,
          "units": -4.2845,
          "totalStake": 8.0,
          "winRate": 0.25,
          "roi": -0.5356
        }
      }
    }
  },
  "lifetime": {
    "picks": 676,
    "wins": 336,
    "losses": 266,
    "pushes": 22,
    "voids": 52,
    "units": 29.6785,
    "totalStake": 624.0,
    "winRate": 0.5581,
    "roi": 0.0476,
    "by_market": {
      "F5_ML": {
        "picks": 139,
        "wins": 67,
        "losses": 52,
        "pushes": 18,
        "voids": 2,
        "units": 9.1983,
        "totalStake": 137.0,
        "winRate": 0.563,
        "roi": 0.0671
      },
      "Hits": {
        "picks": 166,
        "wins": 73,
        "losses": 52,
        "pushes": 0,
        "voids": 41,
        "units": 5.5529,
        "totalStake": 125.0,
        "winRate": 0.584,
        "roi": 0.0444
      },
      "K": {
        "picks": 36,
        "wins": 17,
        "losses": 17,
        "pushes": 0,
        "voids": 2,
        "units": -2.1789,
        "totalStake": 34.0,
        "winRate": 0.5,
        "roi": -0.0641
      },
      "ML": {
        "picks": 174,
        "wins": 85,
        "losses": 86,
        "pushes": 0,
        "voids": 3,
        "units": -11.3574,
        "totalStake": 171.0,
        "winRate": 0.4971,
        "roi": -0.0664
      },
      "Total": {
        "picks": 142,
        "wins": 86,
        "losses": 51,
        "pushes": 3,
        "voids": 2,
        "units": 27.3698,
        "totalStake": 140.0,
        "winRate": 0.6277,
        "roi": 0.1955
      },
      "RL": {
        "picks": 7,
        "wins": 5,
        "losses": 2,
        "pushes": 0,
        "voids": 0,
        "units": 3.2847,
        "totalStake": 7.0,
        "winRate": 0.7143,
        "roi": 0.4692
      },
      "F5_Total": {
        "picks": 4,
        "wins": 0,
        "losses": 3,
        "pushes": 1,
        "voids": 0,
        "units": -3.0,
        "totalStake": 4.0,
        "winRate": 0.0,
        "roi": -0.75
      },
      "NRFI": {
        "picks": 1,
        "wins": 0,
        "losses": 1,
        "pushes": 0,
        "voids": 0,
        "units": -1.0,
        "totalStake": 1.0,
        "winRate": 0.0,
        "roi": -1.0
      },
      "TotalBases": {
        "picks": 7,
        "wins": 3,
        "losses": 2,
        "pushes": 0,
        "voids": 2,
        "units": 1.8091,
        "totalStake": 5.0,
        "winRate": 0.6,
        "roi": 0.3618
      }
    },
    "by_tier": {
      "watch": {
        "picks": 452,
        "wins": 219,
        "losses": 174,
        "pushes": 17,
        "voids": 42,
        "units": 23.8171,
        "totalStake": 410.0,
        "winRate": 0.5573,
        "roi": 0.0581
      },
      "B": {
        "picks": 158,
        "wins": 85,
        "losses": 63,
        "pushes": 4,
        "voids": 6,
        "units": 9.1562,
        "totalStake": 152.0,
        "winRate": 0.5743,
        "roi": 0.0602
      },
      "C": {
        "picks": 43,
        "wins": 20,
        "losses": 20,
        "pushes": 0,
        "voids": 3,
        "units": -3.9904,
        "totalStake": 40.0,
        "winRate": 0.5,
        "roi": -0.0998
      },
      "A": {
        "picks": 9,
        "wins": 6,
        "losses": 1,
        "pushes": 1,
        "voids": 1,
        "units": 3.8778,
        "totalStake": 8.0,
        "winRate": 0.8571,
        "roi": 0.4847
      },
      "b": {
        "picks": 6,
        "wins": 4,
        "losses": 2,
        "pushes": 0,
        "voids": 0,
        "units": 1.1023,
        "totalStake": 6.0,
        "winRate": 0.6667,
        "roi": 0.1837
      },
      "c": {
        "picks": 8,
        "wins": 2,
        "losses": 6,
        "pushes": 0,
        "voids": 0,
        "units": -4.2845,
        "totalStake": 8.0,
        "winRate": 0.25,
        "roi": -0.5356
      }
    }
  },
  "recent14": {
    "picks": 676,
    "wins": 336,
    "losses": 266,
    "pushes": 22,
    "voids": 52,
    "units": 29.6785,
    "totalStake": 624.0,
    "winRate": 0.5581,
    "roi": 0.0476,
    "by_market": {
      "F5_ML": {
        "picks": 139,
        "wins": 67,
        "losses": 52,
        "pushes": 18,
        "voids": 2,
        "units": 9.1983,
        "totalStake": 137.0,
        "winRate": 0.563,
        "roi": 0.0671
      },
      "Hits": {
        "picks": 166,
        "wins": 73,
        "losses": 52,
        "pushes": 0,
        "voids": 41,
        "units": 5.5529,
        "totalStake": 125.0,
        "winRate": 0.584,
        "roi": 0.0444
      },
      "K": {
        "picks": 36,
        "wins": 17,
        "losses": 17,
        "pushes": 0,
        "voids": 2,
        "units": -2.1789,
        "totalStake": 34.0,
        "winRate": 0.5,
        "roi": -0.0641
      },
      "ML": {
        "picks": 174,
        "wins": 85,
        "losses": 86,
        "pushes": 0,
        "voids": 3,
        "units": -11.3574,
        "totalStake": 171.0,
        "winRate": 0.4971,
        "roi": -0.0664
      },
      "Total": {
        "picks": 142,
        "wins": 86,
        "losses": 51,
        "pushes": 3,
        "voids": 2,
        "units": 27.3698,
        "totalStake": 140.0,
        "winRate": 0.6277,
        "roi": 0.1955
      },
      "RL": {
        "picks": 7,
        "wins": 5,
        "losses": 2,
        "pushes": 0,
        "voids": 0,
        "units": 3.2847,
        "totalStake": 7.0,
        "winRate": 0.7143,
        "roi": 0.4692
      },
      "F5_Total": {
        "picks": 4,
        "wins": 0,
        "losses": 3,
        "pushes": 1,
        "voids": 0,
        "units": -3.0,
        "totalStake": 4.0,
        "winRate": 0.0,
        "roi": -0.75
      },
      "NRFI": {
        "picks": 1,
        "wins": 0,
        "losses": 1,
        "pushes": 0,
        "voids": 0,
        "units": -1.0,
        "totalStake": 1.0,
        "winRate": 0.0,
        "roi": -1.0
      },
      "TotalBases": {
        "picks": 7,
        "wins": 3,
        "losses": 2,
        "pushes": 0,
        "voids": 2,
        "units": 1.8091,
        "totalStake": 5.0,
        "winRate": 0.6,
        "roi": 0.3618
      }
    },
    "by_tier": {
      "watch": {
        "picks": 452,
        "wins": 219,
        "losses": 174,
        "pushes": 17,
        "voids": 42,
        "units": 23.8171,
        "totalStake": 410.0,
        "winRate": 0.5573,
        "roi": 0.0581
      },
      "B": {
        "picks": 158,
        "wins": 85,
        "losses": 63,
        "pushes": 4,
        "voids": 6,
        "units": 9.1562,
        "totalStake": 152.0,
        "winRate": 0.5743,
        "roi": 0.0602
      },
      "C": {
        "picks": 43,
        "wins": 20,
        "losses": 20,
        "pushes": 0,
        "voids": 3,
        "units": -3.9904,
        "totalStake": 40.0,
        "winRate": 0.5,
        "roi": -0.0998
      },
      "A": {
        "picks": 9,
        "wins": 6,
        "losses": 1,
        "pushes": 1,
        "voids": 1,
        "units": 3.8778,
        "totalStake": 8.0,
        "winRate": 0.8571,
        "roi": 0.4847
      },
      "b": {
        "picks": 6,
        "wins": 4,
        "losses": 2,
        "pushes": 0,
        "voids": 0,
        "units": 1.1023,
        "totalStake": 6.0,
        "winRate": 0.6667,
        "roi": 0.1837
      },
      "c": {
        "picks": 8,
        "wins": 2,
        "losses": 6,
        "pushes": 0,
        "voids": 0,
        "units": -4.2845,
        "totalStake": 8.0,
        "winRate": 0.25,
        "roi": -0.5356
      }
    }
  },
  "recent30": {
    "picks": 676,
    "wins": 336,
    "losses": 266,
    "pushes": 22,
    "voids": 52,
    "units": 29.6785,
    "totalStake": 624.0,
    "winRate": 0.5581,
    "roi": 0.0476,
    "by_market": {
      "F5_ML": {
        "picks": 139,
        "wins": 67,
        "losses": 52,
        "pushes": 18,
        "voids": 2,
        "units": 9.1983,
        "totalStake": 137.0,
        "winRate": 0.563,
        "roi": 0.0671
      },
      "Hits": {
        "picks": 166,
        "wins": 73,
        "losses": 52,
        "pushes": 0,
        "voids": 41,
        "units": 5.5529,
        "totalStake": 125.0,
        "winRate": 0.584,
        "roi": 0.0444
      },
      "K": {
        "picks": 36,
        "wins": 17,
        "losses": 17,
        "pushes": 0,
        "voids": 2,
        "units": -2.1789,
        "totalStake": 34.0,
        "winRate": 0.5,
        "roi": -0.0641
      },
      "ML": {
        "picks": 174,
        "wins": 85,
        "losses": 86,
        "pushes": 0,
        "voids": 3,
        "units": -11.3574,
        "totalStake": 171.0,
        "winRate": 0.4971,
        "roi": -0.0664
      },
      "Total": {
        "picks": 142,
        "wins": 86,
        "losses": 51,
        "pushes": 3,
        "voids": 2,
        "units": 27.3698,
        "totalStake": 140.0,
        "winRate": 0.6277,
        "roi": 0.1955
      },
      "RL": {
        "picks": 7,
        "wins": 5,
        "losses": 2,
        "pushes": 0,
        "voids": 0,
        "units": 3.2847,
        "totalStake": 7.0,
        "winRate": 0.7143,
        "roi": 0.4692
      },
      "F5_Total": {
        "picks": 4,
        "wins": 0,
        "losses": 3,
        "pushes": 1,
        "voids": 0,
        "units": -3.0,
        "totalStake": 4.0,
        "winRate": 0.0,
        "roi": -0.75
      },
      "NRFI": {
        "picks": 1,
        "wins": 0,
        "losses": 1,
        "pushes": 0,
        "voids": 0,
        "units": -1.0,
        "totalStake": 1.0,
        "winRate": 0.0,
        "roi": -1.0
      },
      "TotalBases": {
        "picks": 7,
        "wins": 3,
        "losses": 2,
        "pushes": 0,
        "voids": 2,
        "units": 1.8091,
        "totalStake": 5.0,
        "winRate": 0.6,
        "roi": 0.3618
      }
    },
    "by_tier": {
      "watch": {
        "picks": 452,
        "wins": 219,
        "losses": 174,
        "pushes": 17,
        "voids": 42,
        "units": 23.8171,
        "totalStake": 410.0,
        "winRate": 0.5573,
        "roi": 0.0581
      },
      "B": {
        "picks": 158,
        "wins": 85,
        "losses": 63,
        "pushes": 4,
        "voids": 6,
        "units": 9.1562,
        "totalStake": 152.0,
        "winRate": 0.5743,
        "roi": 0.0602
      },
      "C": {
        "picks": 43,
        "wins": 20,
        "losses": 20,
        "pushes": 0,
        "voids": 3,
        "units": -3.9904,
        "totalStake": 40.0,
        "winRate": 0.5,
        "roi": -0.0998
      },
      "A": {
        "picks": 9,
        "wins": 6,
        "losses": 1,
        "pushes": 1,
        "voids": 1,
        "units": 3.8778,
        "totalStake": 8.0,
        "winRate": 0.8571,
        "roi": 0.4847
      },
      "b": {
        "picks": 6,
        "wins": 4,
        "losses": 2,
        "pushes": 0,
        "voids": 0,
        "units": 1.1023,
        "totalStake": 6.0,
        "winRate": 0.6667,
        "roi": 0.1837
      },
      "c": {
        "picks": 8,
        "wins": 2,
        "losses": 6,
        "pushes": 0,
        "voids": 0,
        "units": -4.2845,
        "totalStake": 8.0,
        "winRate": 0.25,
        "roi": -0.5356
      }
    }
  }
}