{
  "asOf": "2026-05-01T18:10:45Z",
  "date": "2026-05-01",
  "slateSize": 15,
  "matched": 15,
  "source": "the-odds-api.com consensus across major US books",
  "games": {
    "824686": {
      "moneyline": {
        "away": 121,
        "home": -147,
        "book": "consensus"
      },
      "total": {
        "line": 7.0,
        "over": -115,
        "under": -105
      },
      "runline": {
        "spread": -1.5,
        "favSide": "home",
        "favPrice": 157,
        "dogPrice": -194
      }
    },
    "824287": {
      "moneyline": {
        "away": -102,
        "home": -118,
        "book": "consensus"
      },
      "total": {
        "line": 8.0,
        "over": -110,
        "under": -110
      },
      "runline": {
        "spread": -1.5,
        "favSide": "away",
        "favPrice": 161,
        "dogPrice": -197
      }
    },
    "823389": {
      "moneyline": {
        "away": 114,
        "home": -136,
        "book": "consensus"
      },
      "total": {
        "line": 8.0,
        "over": -118,
        "under": -103
      },
      "runline": {
        "spread": -1.5,
        "favSide": "home",
        "favPrice": 159,
        "dogPrice": -197
      }
    },
    "822744": {
      "moneyline": {
        "away": -158,
        "home": 130,
        "book": "consensus"
      },
      "total": {
        "line": 8.0,
        "over": -107,
        "under": -112
      },
      "runline": {
        "spread": -1.5,
        "favSide": "away",
        "favPrice": 108,
        "dogPrice": -130
      }
    },
    "823557": {
      "moneyline": {
        "away": 154,
        "home": -184,
        "book": "consensus"
      },
      "total": {
        "line": 8.5,
        "over": -118,
        "under": -103
      },
      "runline": {
        "spread": -1.5,
        "favSide": "home",
        "favPrice": 110,
        "dogPrice": -131
      }
    },
    "824772": {
      "moneyline": {
        "away": 104,
        "home": -125,
        "book": "consensus"
      },
      "total": {
        "line": 9.5,
        "over": 101,
        "under": -121
      },
      "runline": {
        "spread": -1.5,
        "favSide": "away",
        "favPrice": 159,
        "dogPrice": -194
      }
    },
    "822990": {
      "moneyline": {
        "away": 119,
        "home": -143,
        "book": "consensus"
      },
      "total": {
        "line": 7.5,
        "over": -115,
        "under": -105
      },
      "runline": {
        "spread": -1.5,
        "favSide": "home",
        "favPrice": 149,
        "dogPrice": -183
      }
    },
    "823877": {
      "moneyline": {
        "away": -121,
        "home": -100,
        "book": "consensus"
      },
      "total": {
        "line": 8.0,
        "over": -105,
        "under": -115
      },
      "runline": {
        "spread": -1.5,
        "favSide": "away",
        "favPrice": 140,
        "dogPrice": -170
      }
    },
    "823713": {
      "moneyline": {
        "away": -107,
        "home": -112,
        "book": "consensus"
      },
      "total": {
        "line": 8.5,
        "over": -116,
        "under": -105
      },
      "runline": {
        "spread": -1.5,
        "favSide": "away",
        "favPrice": 150,
        "dogPrice": -186
      }
    },
    "823066": {
      "moneyline": {
        "away": -183,
        "home": 152,
        "book": "consensus"
      },
      "total": {
        "line": 8.0,
        "over": -116,
        "under": -105
      },
      "runline": {
        "spread": -1.5,
        "favSide": "away",
        "favPrice": -107,
        "dogPrice": -114
      }
    },
    "824366": {
      "moneyline": {
        "away": -185,
        "home": 154,
        "book": "consensus"
      },
      "total": {
        "line": 11.0,
        "over": -103,
        "under": -119
      },
      "runline": {
        "spread": -1.5,
        "favSide": "away",
        "favPrice": -123,
        "dogPrice": 102
      }
    },
    "824041": {
      "moneyline": {
        "away": -125,
        "home": 104,
        "book": "consensus"
      },
      "total": {
        "line": 9.0,
        "over": -113,
        "under": -107
      },
      "runline": {
        "spread": -1.5,
        "favSide": "away",
        "favPrice": 128,
        "dogPrice": -155
      }
    },
    "825012": {
      "moneyline": {
        "away": -115,
        "home": -103,
        "book": "consensus"
      },
      "total": {
        "line": 9.5,
        "over": -103,
        "under": -116
      },
      "runline": {
        "spread": -1.5,
        "favSide": "away",
        "favPrice": 138,
        "dogPrice": -164
      }
    },
    "823309": {
      "moneyline": {
        "away": 124,
        "home": -151,
        "book": "consensus"
      },
      "total": {
        "line": 8.0,
        "over": -114,
        "under": -107
      },
      "runline": {
        "spread": -1.5,
        "favSide": "home",
        "favPrice": 143,
        "dogPrice": -176
      }
    },
    "823146": {
      "moneyline": {
        "away": 125,
        "home": -149,
        "book": "consensus"
      },
      "total": {
        "line": 7.0,
        "over": -112,
        "under": -108
      },
      "runline": {
        "spread": -1.5,
        "favSide": "home",
        "favPrice": 147,
        "dogPrice": -181
      }
    }
  }
}
